nonebot_plugin_kawaii_logos/__init__.py
nonebot_plugin_kawaii_logos/command.py
nonebot_plugin_kawaii_logos/config.py
nonebot_plugin_kawaii_logos/draw.py
nonebot_plugin_kawaii_logos/tools.py
nonebot_plugin_kawaii_logos-0.0.0.1.dist-info/LICENSE
nonebot_plugin_kawaii_logos-0.0.0.1.dist-info/METADATA
nonebot_plugin_kawaii_logos-0.0.0.1.dist-info/WHEEL
nonebot_plugin_kawaii_logos-0.0.0.1.dist-info/RECORD
