Metadata-Version: 2.3
Name: nonebot-plugin-kawaii-logos
Version: 0.0.0.1
Summary: logo生成器
License: MIT
Keywords: nonebot2,qbittorrent
Author: SuperGuGuGu
Author-email: from89917812@163.com
Requires-Python: >=3.10,<4.0
Classifier: License :: OSI Approved :: MIT License
Classifier: Programming Language :: Python :: 3
Classifier: Programming Language :: Python :: 3.10
Classifier: Programming Language :: Python :: 3.11
Classifier: Programming Language :: Python :: 3.12
Classifier: Programming Language :: Python :: 3.13
Requires-Dist: httpx (>=0.23)
Requires-Dist: matplotlib (>=3.9.0)
Requires-Dist: nonebot-plugin-localstore (>=0.6.0)
Requires-Dist: nonebot-plugin-send-anything-anywhere (>=0.7.0)
Requires-Dist: nonebot2 (>=2.2.0)
Requires-Dist: opencv-python (>=4.9.0)
Requires-Dist: pathlib (>=1.0)
Requires-Dist: pillow (>=11.0.0)
Project-URL: Repository, https://github.com/SuperGuGuGu/nonebot-plugin-kawaii-logos
